CHANGELOG.md
LICENSE
README.md
fastapi_rest/__init__.py
fastapi_rest/pagination.py
fastapi_rest/resource.py
fastapi_rest-0.1.1.dist-info/LICENSE
fastapi_rest-0.1.1.dist-info/WHEEL
fastapi_rest-0.1.1.dist-info/METADATA
fastapi_rest-0.1.1.dist-info/RECORD
