Metadata-Version: 2.1
Name: fastapi-rest
Version: 0.1.1
Summary: Fast restful API based on FastAPI and TortoiseORM
Home-page: https://github.com/long2ice/fastapi-rest
License: Apache2.0
Keywords: fastapi,restful,tortoise-orm
Author: long2ice
Author-email: long2ice@gmail.com
Requires-Python: >=3.7,<4.0
Classifier: License :: Other/Proprietary License
Classifier: Programming Language :: Python :: 3
Classifier: Programming Language :: Python :: 3.7
Classifier: Programming Language :: Python :: 3.8
Classifier: Programming Language :: Python :: 3.9
Requires-Dist: fastapi
Requires-Dist: tortoise-orm
Project-URL: Documentation, https://github.com/long2ice/fastapi-rest
Project-URL: Repository, https://github.com/long2ice/fastapi-rest.git
